{
  "required": true,
  "package": "org.daylight.mixin.client",
  "compatibilityLevel": "JAVA_21",
  "client": [
    "CatEntityAccessor",
    "CatEntityMixin",
    "CatEntityRendererMixin",
    "CatEntityRenderStateMixin",
    "EntityGuiElementRendererMixin",
    "EntityGuiElementRenderStateMixin",
    "EntityRenderDispatcherMixin",
    "EntityRendererAccessor",
    "EntityRendererMixin",
    "LimbAnimatorAccessor",
    "LivingEntityRendererMixin",
    "PlayerEntityRendererMixin",
    "SpecialGuiElementRendererAccessor"
  ],
  "verbose": false,
  "injectors": {
    "defaultRequire": 1
  },
  "mixins": [
    "EntityMixin"
  ]
}